pyclog/__init__.py
pyclog/cli.py
pyclog/constants.py
pyclog/exceptions.py
pyclog/handler.py
pyclog/reader.py
pyclog/writer.py
pyclog-0.1.3.dist-info/licenses/LICENSE
pyclog-0.1.3.dist-info/METADATA
pyclog-0.1.3.dist-info/WHEEL
pyclog-0.1.3.dist-info/entry_points.txt
pyclog-0.1.3.dist-info/top_level.txt
pyclog-0.1.3.dist-info/RECORD
