Metadata-Version: 2.4
Name: pyclog
Version: 0.1.3
Summary: A Python package for reading and writing .clog files with logging integration.
Author-email: Akanyi <sakayezq@gmail.com>
License: MIT
Project-URL: Homepage, https://github.com/Akanyi/pyclog
Project-URL: Bug Tracker, https://github.com/Akanyi/pyclog/issues
Classifier: Development Status :: 4 - Beta
Classifier: License :: OSI Approved :: MIT License
Classifier: Operating System :: OS Independent
Classifier: Intended Audience :: Developers
Classifier: Topic :: Software Development :: Libraries :: Python Modules
Classifier: Topic :: System :: Logging
Classifier: Programming Language :: Python :: 3.8
Classifier: Programming Language :: Python :: 3.9
Classifier: Programming Language :: Python :: 3.10
Classifier: Programming Language :: Python :: 3.11
Classifier: Programming Language :: Python :: 3.12
Classifier: Programming Language :: Python :: 3.13
Requires-Python: >=3.8
License-File: LICENSE
Provides-Extra: zstandard
Requires-Dist: zstandard; extra == "zstandard"
Provides-Extra: test
Requires-Dist: pytest; extra == "test"
Requires-Dist: pytest-cov; extra == "test"
Requires-Dist: pytest-mock; extra == "test"
Dynamic: license-file
